indieweb_utils/__init__.py
indieweb_utils/constants.py
indieweb_utils/feeds/__init__.py
indieweb_utils/feeds/discovery.py
indieweb_utils/feeds/poll.py
indieweb_utils/feeds/urls.py
indieweb_utils/images/__init__.py
indieweb_utils/images/resize.py
indieweb_utils/indieauth/__init__.py
indieweb_utils/indieauth/constants.py
indieweb_utils/indieauth/flask.py
indieweb_utils/indieauth/happ.py
indieweb_utils/indieauth/header_discovery.py
indieweb_utils/indieauth/profile.py
indieweb_utils/indieauth/relmeauth.py
indieweb_utils/indieauth/scopes.py
indieweb_utils/indieauth/server.py
indieweb_utils/pagination/__init__.py
indieweb_utils/pagination/paginator.py
indieweb_utils/parsing/__init__.py
indieweb_utils/parsing/parse.py
indieweb_utils/posts/__init__.py
indieweb_utils/posts/discovery.py
indieweb_utils/posts/in_reply_to.py
indieweb_utils/posts/page_name.py
indieweb_utils/posts/posse.py
indieweb_utils/posts/representative_h_card.py
indieweb_utils/replies/__init__.py
indieweb_utils/replies/context.py
indieweb_utils/rsd/__init__.py
indieweb_utils/rsd/discover.py
indieweb_utils/salmention/__init__.py
indieweb_utils/salmention/salmention.py
indieweb_utils/trackback/__init__.py
indieweb_utils/trackback/receive.py
indieweb_utils/trackback/send.py
indieweb_utils/utils/__init__.py
indieweb_utils/utils/autotag.py
indieweb_utils/utils/footnotes.py
indieweb_utils/utils/rel_edit.py
indieweb_utils/utils/url_summary.py
indieweb_utils/utils/url_summary_templates.py
indieweb_utils/utils/urls.py
indieweb_utils/utils/web_bot_auth.py
indieweb_utils/webmentions/__init__.py
indieweb_utils/webmentions/discovery.py
indieweb_utils/webmentions/send.py
indieweb_utils/webmentions/validate.py
indieweb_utils-0.10.0.dist-info/licenses/LICENSE.md
indieweb_utils-0.10.0.dist-info/METADATA
indieweb_utils-0.10.0.dist-info/WHEEL
indieweb_utils-0.10.0.dist-info/top_level.txt
indieweb_utils-0.10.0.dist-info/RECORD
