Metadata-Version: 2.4
Name: indieweb-utils
Version: 0.10.0
Summary:  Building blocks for IndieWeb applications.
Home-page: https://github.com/capjamesg/indieweb-utils
Author: capjamesg
Author-email: jamesg@jamesg.blog
Project-URL: Bug Tracker, https://github.com/capjamesg/indieweb-utils/issues
Classifier: Programming Language :: Python :: 3
Classifier: License :: OSI Approved :: MIT License
Classifier: Operating System :: OS Independent
Requires-Python: >=3.6
License-File: LICENSE.md
Requires-Dist: mf2py
Requires-Dist: requests
Requires-Dist: beautifulsoup4
Requires-Dist: lxml
Requires-Dist: Pillow
Requires-Dist: granary
Requires-Dist: http_message_signatures
Requires-Dist: python-jose
Dynamic: author
Dynamic: author-email
Dynamic: classifier
Dynamic: description
Dynamic: description-content-type
Dynamic: home-page
Dynamic: license-file
Dynamic: project-url
Dynamic: requires-dist
Dynamic: requires-python
Dynamic: summary
